q3huff.cpython-37m-x86_64-linux-gnu.so
q3huff-0.4.1.dist-info/COPYING
q3huff-0.4.1.dist-info/top_level.txt
q3huff-0.4.1.dist-info/RECORD
q3huff-0.4.1.dist-info/METADATA
q3huff-0.4.1.dist-info/WHEEL
